rigidpy/__init__.py
rigidpy/circuit.py
rigidpy/circuit_length.py
rigidpy/circuit_volume.py
rigidpy/configuration.py
rigidpy/framework.py
rigidpy-0.0.8.dist-info/LICENSE
rigidpy-0.0.8.dist-info/METADATA
rigidpy-0.0.8.dist-info/WHEEL
rigidpy-0.0.8.dist-info/top_level.txt
rigidpy-0.0.8.dist-info/RECORD
