Metadata-Version: 2.1
Name: rigidpy
Version: 0.0.8
Summary: rigidpy package for rigidity analysis
Home-page: https://github.com/vfaghirh/rigidpy
Author: Varda Faghir Hagh, Mahdi Sadjadi
Author-email: vardahagh@uchicago.edu
License: MIT License        
Keywords: rigidity physics math python flexibility condensedmatter
Platform: UNKNOWN
Requires-Python: >=3.5
License-File: LICENSE
